hydro_update/__init__.py
hydro_update/hydro_update.py
hydro_update/performance_criteria.py
hydro_update/plot.py
hydro_update/version.py
hydro_update-0.0.1.dist-info/LICENCE
hydro_update-0.0.1.dist-info/METADATA
hydro_update-0.0.1.dist-info/WHEEL
hydro_update-0.0.1.dist-info/top_level.txt
hydro_update-0.0.1.dist-info/RECORD
