Metadata-Version: 2.1
Name: hydro_update
Version: 0.0.1
Summary: update hydrologic forecasts
Home-page: https://github.com/3Benjamin/wadaba.git
Author: Seck Oumar Tientega
Author-email: oumartientegaseck@gmail.com
Classifier: Programming Language :: Python :: 3
Classifier: License :: OSI Approved :: MIT License
Classifier: Operating System :: OS Independent
Requires-Python: >=3.7
License-File: LICENCE
